[{"tag": "Default", "title": "The Giver (The Giver Quartet #1)", "price": "\u00a312.30", "rating": "One", "image_urls": ["http://books.toscrape.com/media/cache/fe/a1/fea18082a98781b8e87bdf99065f4887.jpg"], "product_desc": "Featuring photographic artwork from the feature film on the cover, this handsome edition of The Giver is perfect for fans of the movie and the literary classic. Lois Lowry's 1994 Newbery Medal\u2013winning tale has become one of the most influential novels of our time. The haunting story centers on Jonas who lives in a seemingly ideal, if colorless, world of conformity and cont Featuring\u00a0 photographic artwork from the feature film on the cover, this handsome edition of The Giver\u00a0 is \u00a0perfect for fans of the movie and the\u00a0 literary classic. Lois Lowry's 1994 Newbery Medal\u2013winning tale has become one of the most influential novels of our time. The haunting story centers on \u00a0Jonas who lives in a seemingly ideal, if colorless, world of conformity and contentment. Not until he is given his life assignment as the Receiver of Memory does he begin to understand the dark, complex secrets behind his fragile community. Lois Lowry has written three companion novels to The Giver, including Gathering Blue, Messenger, and Son. ...more"}]